IMC_tool/__init__.py
IMC_tool/convert_mcd.py
IMC_tool/display_markers.py
IMC_tool/function.py
IMC_tool/script_visualize.py
IMC_tool/visualize.py
IMC_tool/visualize_marker.py
tests/__init__.py
tests/test_functions.py
IMC_tool-0.0.1.dist-info/METADATA
IMC_tool-0.0.1.dist-info/WHEEL
IMC_tool-0.0.1.dist-info/entry_points.txt
IMC_tool-0.0.1.dist-info/top_level.txt
IMC_tool-0.0.1.dist-info/RECORD
